rhinoplasty/__init__.py
rhinoplasty/_version.py
rhinoplasty/timed.py
rhinoplasty/wrapper.py
rhinoplasty/compressed_tests/__init__.py
rhinoplasty/compressed_tests/plugin.py
rhinoplasty/rich_errors/__init__.py
rhinoplasty/rich_errors/_decorators.py
rhinoplasty/rich_errors/_errors.py
rhinoplasty/rich_errors/plugin.py
rhinoplasty-0.7.4.dist-info/AUTHORS.txt
rhinoplasty-0.7.4.dist-info/LICENSE
rhinoplasty-0.7.4.dist-info/METADATA
rhinoplasty-0.7.4.dist-info/WHEEL
rhinoplasty-0.7.4.dist-info/entry_points.txt
rhinoplasty-0.7.4.dist-info/top_level.txt
rhinoplasty-0.7.4.dist-info/RECORD
