Metadata-Version: 2.1
Name: rhinoplasty
Version: 0.7.4
Summary: Extra tools for the Nose test runner.
Home-page: https://pypi.python.org/pypi/rhinoplasty/
Author: Gary Donovan and contributors
Author-email: gazza@gazza.id.au
License: LGPL
Keywords: Nose test unittest
Platform: UNKNOWN
Classifier: Development Status :: 4 - Beta
Classifier: Environment :: Plugins
Classifier: Intended Audience :: Developers
Classifier: License :: OSI Approved :: GNU Library or Lesser General Public License (LGPL)
Classifier: Natural Language :: English
Classifier: Operating System :: OS Independent
Classifier: Programming Language :: Python :: 2
Classifier: Programming Language :: Python :: 3
Classifier: Topic :: Software Development :: Testing
Requires-Dist: nose
Requires-Dist: six
